{"name":"validar  que el nombre del producto seleccionados en el carrito","id":"realizar-la-validacion-del-nombre-del-producto-seleccionado-en-el-carrito-tenga-el-mismo-nombre;validar--que-el-nombre-del-producto-seleccionados-en-el-carrito","testSteps":[{"number":1,"description":"1: validar  que el nombre del producto seleccionados en el carrito ({Ciudad\u003dMedellín, Almacen\u003dExito Envigado, NombreProductoUno\u003dPOKER, cantidadProductoUno\u003d5, NombreProductoDos\u003dCOSTENA, cantidadProductoDos\u003d1, NombreProductoTres\u003dCLUBCOLOMBIA, cantidadProductoTres\u003d2, NombreProductoCuatro\u003dCORONA, cantidadProductoCuatro\u003d3, NombreProductoCinco\u003dANDINA, cantidadProductoCinco\u003d4})","duration":12558,"startTime":"2023-07-29T14:17:15.639564-05:00[America/Bogota]","screenshots":[{"screenshot":"386223cf3e2dd94ab427d985ab0dc339c1d2f6bb33006daeeae92ff36541a4fe.png","timeStamp":1690658248197}],"result":"SUCCESS","precondition":false,"level":0,"lineNumber":17,"children":[{"number":2,"description":"Dado que estoy en la pagina del exito","duration":8570,"startTime":"2023-07-29T14:17:15.755423600-05:00[America/Bogota]","screenshots":[{"screenshot":"87abe40c7cf0361aec06a9a3d2ee561fe562fb7d2409ae630c987daaf439bf59.png","timeStamp":1690658244326}],"result":"SUCCESS","precondition":false,"level":1,"children":[{"number":3,"description":" abrir pagina","duration":8163,"startTime":"2023-07-29T14:17:16.156416400-05:00[America/Bogota]","screenshots":[{"screenshot":"87abe40c7cf0361aec06a9a3d2ee561fe562fb7d2409ae630c987daaf439bf59.png","timeStamp":1690658244320}],"result":"SUCCESS","precondition":false,"level":2,"children":[{"number":4,"description":" opens the Pagina exito","duration":8127,"startTime":"2023-07-29T14:17:16.178543700-05:00[America/Bogota]","screenshots":[{"screenshot":"87abe40c7cf0361aec06a9a3d2ee561fe562fb7d2409ae630c987daaf439bf59.png","timeStamp":1690658244305}],"result":"SUCCESS","precondition":false,"level":3}]}]},{"number":5,"description":"Cuando elijo una categoria","duration":2847,"startTime":"2023-07-29T14:17:24.329186-05:00[America/Bogota]","screenshots":[{"screenshot":"87abe40c7cf0361aec06a9a3d2ee561fe562fb7d2409ae630c987daaf439bf59.png","timeStamp":1690658244331},{"screenshot":"a9c8771a78f791ef22b6c424dea26e5e871338ad3405bb87b7e21f20bbb8651b.png","timeStamp":1690658247176}],"result":"SUCCESS","precondition":false,"level":1,"children":[{"number":6,"description":" categoria","duration":2829,"startTime":"2023-07-29T14:17:24.343138900-05:00[America/Bogota]","screenshots":[{"screenshot":"87abe40c7cf0361aec06a9a3d2ee561fe562fb7d2409ae630c987daaf439bf59.png","timeStamp":1690658244348},{"screenshot":"a9c8771a78f791ef22b6c424dea26e5e871338ad3405bb87b7e21f20bbb8651b.png","timeStamp":1690658247173}],"result":"SUCCESS","precondition":false,"level":2,"children":[{"number":7,"description":" clicks on Menu","duration":1946,"startTime":"2023-07-29T14:17:24.381036100-05:00[America/Bogota]","screenshots":[{"screenshot":"10a8d9843161c90b9cbcfcb67da56df5eef1fd9e21c87181f5820ee65fdf3bc1.png","timeStamp":1690658244893},{"screenshot":"d52c90799841ebef1c6bb4cfaa0e07d8608351ff0d4d97eda95d5c15ebb35ab2.png","timeStamp":1690658246327}],"result":"SUCCESS","precondition":false,"level":3},{"number":8,"description":" clicks on ","duration":708,"startTime":"2023-07-29T14:17:26.460505800-05:00[America/Bogota]","screenshots":[{"screenshot":"b7b46e7a16e728207c0d512dddf98e02d37fa3bce95209d6b3fa78219a6635a7.png","timeStamp":1690658246722},{"screenshot":"a9c8771a78f791ef22b6c424dea26e5e871338ad3405bb87b7e21f20bbb8651b.png","timeStamp":1690658247169}],"result":"SUCCESS","precondition":false,"level":3}]}]},{"number":9,"description":"Y luego selecciono una subcategoria","duration":980,"startTime":"2023-07-29T14:17:27.179024-05:00[America/Bogota]","screenshots":[{"screenshot":"a9c8771a78f791ef22b6c424dea26e5e871338ad3405bb87b7e21f20bbb8651b.png","timeStamp":1690658247181},{"screenshot":"386223cf3e2dd94ab427d985ab0dc339c1d2f6bb33006daeeae92ff36541a4fe.png","timeStamp":1690658248159}],"result":"SUCCESS","precondition":false,"level":1,"children":[{"number":10,"description":" sub categoria","duration":964,"startTime":"2023-07-29T14:17:27.189420400-05:00[America/Bogota]","screenshots":[{"screenshot":"a9c8771a78f791ef22b6c424dea26e5e871338ad3405bb87b7e21f20bbb8651b.png","timeStamp":1690658247191},{"screenshot":"386223cf3e2dd94ab427d985ab0dc339c1d2f6bb33006daeeae92ff36541a4fe.png","timeStamp":1690658248153}],"result":"SUCCESS","precondition":false,"level":2,"children":[{"number":11,"description":" clicks on ","duration":884,"startTime":"2023-07-29T14:17:27.264451400-05:00[America/Bogota]","screenshots":[{"screenshot":"546a22c64978a3713479860a39cd0a02b8a405b43ac5899023eb5ca9c3cdee1e.png","timeStamp":1690658247483},{"screenshot":"386223cf3e2dd94ab427d985ab0dc339c1d2f6bb33006daeeae92ff36541a4fe.png","timeStamp":1690658248148}],"result":"SUCCESS","precondition":false,"level":3}]}]},{"number":12,"description":"Y agrego cinco productos con distintas cantidades al carrito\r\n| Ciudad | Almacen | NombreProductoUno | cantidadProductoUno | NombreProductoDos | cantidadProductoDos | NombreProductoTres | cantidadProductoTres | NombreProductoCuatro | cantidadProductoCuatro | NombreProductoCinco | cantidadProductoCinco |\r\n| Medellín | Exito Envigado | POKER | 5 | COSTENA | 1 | CLUBCOLOMBIA | 2 | CORONA | 3 | ANDINA | 4 |","duration":6,"startTime":"2023-07-29T14:17:28.161831400-05:00[America/Bogota]","screenshots":[{"screenshot":"386223cf3e2dd94ab427d985ab0dc339c1d2f6bb33006daeeae92ff36541a4fe.png","timeStamp":1690658248163},{"screenshot":"386223cf3e2dd94ab427d985ab0dc339c1d2f6bb33006daeeae92ff36541a4fe.png","timeStamp":1690658248168}],"result":"SUCCESS","precondition":false,"level":1},{"number":13,"description":"Y ingreso al carrito de compras","duration":9,"startTime":"2023-07-29T14:17:28.170807800-05:00[America/Bogota]","screenshots":[{"screenshot":"386223cf3e2dd94ab427d985ab0dc339c1d2f6bb33006daeeae92ff36541a4fe.png","timeStamp":1690658248172},{"screenshot":"386223cf3e2dd94ab427d985ab0dc339c1d2f6bb33006daeeae92ff36541a4fe.png","timeStamp":1690658248180}],"result":"SUCCESS","precondition":false,"level":1},{"number":14,"description":"Entonces verifico el nombre de los productos agregados debera ser igual que en el carrito","duration":5,"startTime":"2023-07-29T14:17:28.182774500-05:00[America/Bogota]","screenshots":[{"screenshot":"386223cf3e2dd94ab427d985ab0dc339c1d2f6bb33006daeeae92ff36541a4fe.png","timeStamp":1690658248184},{"screenshot":"386223cf3e2dd94ab427d985ab0dc339c1d2f6bb33006daeeae92ff36541a4fe.png","timeStamp":1690658248188}],"result":"SUCCESS","precondition":false,"level":1}]}],"userStory":{"id":"realizar-la-validacion-del-nombre-del-producto-seleccionado-en-el-carrito-tenga-el-mismo-nombre","storyName":"Realizar la validacion del nombre del producto seleccionado en el carrito tenga el mismo nombre","path":"nombre_producto_carrito.feature","type":"feature"},"featureTag":{"name":"Realizar la validacion del nombre del producto seleccionado en el carrito tenga el mismo nombre","type":"feature","displayName":"Realizar la validacion del nombre del producto seleccionado en el carrito tenga el mismo nombre"},"title":"validar  que el nombre del producto seleccionados en el carrito","description":"","tags":[{"name":"Realizar la validacion del nombre del producto seleccionado en el carrito tenga el mismo nombre","type":"feature","displayName":"Realizar la validacion del nombre del producto seleccionado en el carrito tenga el mismo nombre"}],"startTime":"2023-07-29T14:17:15.523603400-05:00[America/Bogota]","duration":13512,"projectKey":"","driver":"chrome:","isManualTestingUpToDate":false,"dataTable":{"headers":["Ciudad","Almacen","NombreProductoUno","cantidadProductoUno","NombreProductoDos","cantidadProductoDos","NombreProductoTres","cantidadProductoTres","NombreProductoCuatro","cantidadProductoCuatro","NombreProductoCinco","cantidadProductoCinco"],"rows":[{"values":["Medellín","Exito Envigado","POKER","5","COSTENA","1","CLUBCOLOMBIA","2","CORONA","3","ANDINA","4"],"lineNumber":17,"result":"SUCCESS"}],"predefinedRows":true,"scenarioOutline":"Dado que estoy en la pagina del exito\n\rCuando elijo una categoria\n\rY luego selecciono una subcategoria\n\rY agrego cinco productos con distintas cantidades al carrito\n\rY ingreso al carrito de compras\n\rEntonces verifico el nombre de los productos agregados debera ser igual que en el carrito\n\r","dataSetDescriptors":[{"startRow":0,"rowCount":0,"name":"","description":""}]},"manual":false,"testSource":"Cucumber","actors":[{"name":"","can":["browse the web"]}],"result":"SUCCESS","scenarioOutline":"Dado que estoy en la pagina del exito\r\nCuando elijo una categoria\r\nY luego selecciono una subcategoria\r\nY agrego cinco productos con distintas cantidades al carrito\r\n|Ciudad | Almacen | NombreProductoUno | cantidadProductoUno | NombreProductoDos | cantidadProductoDos | NombreProductoTres | cantidadProductoTres | NombreProductoCuatro | cantidadProductoCuatro | NombreProductoCinco | cantidadProductoCinco|\r\n|\u003cCiudad\u003e | \u003cAlmacen\u003e | \u003cNombreProductoUno\u003e | \u003ccantidadProductoUno\u003e | \u003cNombreProductoDos\u003e | \u003ccantidadProductoDos\u003e | \u003cNombreProductoTres\u003e | \u003ccantidadProductoTres\u003e | \u003cNombreProductoCuatro\u003e | \u003ccantidadProductoCuatro\u003e | \u003cNombreProductoCinco\u003e | \u003ccantidadProductoCinco\u003e|\r\nY ingreso al carrito de compras\r\nEntonces verifico el nombre de los productos agregados debera ser igual que en el carrito"}